zrb_ollama/__init__.py
zrb_ollama/__main__.py
zrb_ollama/agent/__init__.py
zrb_ollama/agent/_helper.py
zrb_ollama/agent/agent.py
zrb_ollama/config.py
zrb_ollama/interactive/__init__.py
zrb_ollama/interactive/conversation.py
zrb_ollama/interactive/tool.py
zrb_ollama/task/__init__.py
zrb_ollama/task/llm_task.py
zrb_ollama/tools/__init__.py
zrb_ollama/tools/_helper.py
zrb_ollama/tools/calculate.py
zrb_ollama/tools/get_current_location.py
zrb_ollama/tools/get_current_weather.py
zrb_ollama/tools/git.py
zrb_ollama/tools/open_web_page.py
zrb_ollama/tools/query_internet.py
zrb_ollama/tools/rag.py
zrb_ollama/tools/run_shell_command.py
zrb_ollama-0.2.14.dist-info/METADATA
zrb_ollama-0.2.14.dist-info/WHEEL
zrb_ollama-0.2.14.dist-info/entry_points.txt
zrb_ollama-0.2.14.dist-info/RECORD
