Metadata-Version: 2.1
Name: zrb-ollama
Version: 0.2.14
Summary: Zrb LLM plugin
Home-page: https://github.com/state-alchemists/zrb-ollama
License: AGPL-3.0-or-later
Keywords: Ollama,OpenAI,Bedrock,AI Agent,LLM
Author: Go Frendi
Author-email: gofrendiasgard@gmail.com
Requires-Python: >=3.10.0,<4.0.0
Classifier: License :: OSI Approved :: GNU Affero General Public License v3 or later (AGPLv3+)
Classifier: Programming Language :: Python :: 3
Classifier: Programming Language :: Python :: 3.10
Classifier: Programming Language :: Python :: 3.11
Classifier: Programming Language :: Python :: 3.12
Provides-Extra: aws
Provides-Extra: rag
Requires-Dist: beautifulsoup4 (>=4.12.3,<4.13.0)
Requires-Dist: boto3 (>=1.34.140,<1.35.0) ; extra == "aws"
Requires-Dist: chromadb (>=0.5.3,<0.6.0) ; extra == "rag"
Requires-Dist: json-repair (>=0.28.4,<0.29.0)
Requires-Dist: litellm (>=1.44.8,<1.45.0)
Requires-Dist: pdfplumber (>=0.11.3,<0.12.0) ; extra == "rag"
Requires-Dist: requests (>=2.31.0,<2.32.0)
Requires-Dist: zrb (>=0.25.0)
Project-URL: Documentation, https://github.com/state-alchemists/zrb-ollama
Project-URL: Repository, https://github.com/state-alchemists/zrb-ollama
